tencentcloud/__init__.py
tencentcloud/monitor/__init__.py
tencentcloud/monitor/v20180724/__init__.py
tencentcloud/monitor/v20180724/errorcodes.py
tencentcloud/monitor/v20180724/models.py
tencentcloud/monitor/v20180724/monitor_client.py
tencentcloud/monitor/v20180724/monitor_client_async.py
tencentcloud/monitor/v20230616/__init__.py
tencentcloud/monitor/v20230616/errorcodes.py
tencentcloud/monitor/v20230616/models.py
tencentcloud/monitor/v20230616/monitor_client.py
tencentcloud/monitor/v20230616/monitor_client_async.py
tencentcloud_sdk_python_monitor-3.1.35.dist-info/METADATA
tencentcloud_sdk_python_monitor-3.1.35.dist-info/WHEEL
tencentcloud_sdk_python_monitor-3.1.35.dist-info/top_level.txt
tencentcloud_sdk_python_monitor-3.1.35.dist-info/RECORD
